package_creation_tutorial/__init__.py
package_creation_tutorial/string_ops.py
package_ramy_creation_tutorial-0.1.0.dist-info/METADATA
package_ramy_creation_tutorial-0.1.0.dist-info/WHEEL
package_ramy_creation_tutorial-0.1.0.dist-info/RECORD
