Metadata-Version: 2.4
Name: package-ramy-creation-tutorial
Version: 0.1.0
Summary: A tutorial package for string operations
Author: Ramy Lazghab
Author-email: ramylazghab19@gmail.com
Requires-Python: >=3.12,<4.0
Classifier: Programming Language :: Python :: 3
Classifier: Programming Language :: Python :: 3.12
Classifier: Programming Language :: Python :: 3.13
Classifier: Programming Language :: Python :: 3.14
